README
fixturefactory.py
setup.py
./fixturefactory.py
fixturefactory.egg-info/PKG-INFO
fixturefactory.egg-info/SOURCES.txt
fixturefactory.egg-info/dependency_links.txt
fixturefactory.egg-info/requires.txt
fixturefactory.egg-info/top_level.txt