Metadata-Version: 1.0
Name: fixturefactory
Version: 0.2a
Summary: Factory to generate Django model objects.  Easier than factoryboy and factorygirl
Home-page: git@github.com:adgaudio/fixturefactory.git
Author: Alex Gaudio
Author-email: adgaudio@gmail.com
License: UNKNOWN
Keywords: django factory fixture
Platform: UNKNOWN
